try_analytics.py
try_analytics-0.0.4.dist-info/DESCRIPTION.rst
try_analytics-0.0.4.dist-info/WHEEL
try_analytics-0.0.4.dist-info/RECORD
try_analytics-0.0.4.dist-info/METADATA
try_analytics-0.0.4.dist-info/metadata.json
try_analytics-0.0.4.dist-info/top_level.txt
