Metadata-Version: 2.0
Name: try-analytics
Version: 0.0.4
Summary: Try to collect install stats through google analytics
Home-page: UNKNOWN
Author: ('Joao Pimentel',)
Author-email: joaofelipenp@gmail.com
License: MIT
Keywords: google analytics setup.py
Platform: UNKNOWN
